aiosseclient.py
aiosseclient-0.1.8.dist-info/LICENSE
aiosseclient-0.1.8.dist-info/METADATA
aiosseclient-0.1.8.dist-info/WHEEL
aiosseclient-0.1.8.dist-info/top_level.txt
aiosseclient-0.1.8.dist-info/RECORD
