Metadata-Version: 2.2
Name: aiosseclient
Version: 0.1.8
Summary: Asynchronous Server Sent Event streams client.
Home-page: https://github.com/ebraminio/aiosseclient
Author: Ebrahim Byagowi
Author-email: ebrahim@gnu.org
License: Copyright (c) 2017-2025 Ebrahim Byagowi
Classifier: Intended Audience :: Developers
Classifier: License :: OSI Approved :: MIT License
Classifier: Programming Language :: Python :: 3.9
License-File: LICENSE
Requires-Dist: aiohttp
Dynamic: author
Dynamic: author-email
Dynamic: classifier
Dynamic: description
Dynamic: description-content-type
Dynamic: home-page
Dynamic: license
Dynamic: requires-dist
Dynamic: summary
